krag_mathlib/__init__.py
krag_mathlib/core.py
krag_mathlib/utils.py
krag_mathlib-0.1.17.dist-info/licenses/LICENSE
krag_mathlib-0.1.17.dist-info/METADATA
krag_mathlib-0.1.17.dist-info/WHEEL
krag_mathlib-0.1.17.dist-info/top_level.txt
krag_mathlib-0.1.17.dist-info/RECORD
