Metadata-Version: 2.4
Name: krag_mathlib
Version: 0.1.17
Summary: A clean mathematical utility package.
Author-email: "Kenura R. Gunarathna" <kenuragunarathna@gmail.com>
License: MIT License
Project-URL: Homepage, https://github.com/Kenura-R-Gunarathna/mathlib
Requires-Python: >=3.8
License-File: LICENSE
Provides-Extra: dev
Requires-Dist: pytest>=7.0; extra == "dev"
Requires-Dist: pytest-cov>=4.0; extra == "dev"
Dynamic: license-file
